{"https://profil.gittigidiyor.com/kombidukkani": [{"numberOfReviewsMonths": "930", "positiveScoreRate": "%100", "criterias": {"criteria": {"label1": "\u00dcr\u00fcn\u00fcn a\u00e7\u0131klamalarda anlat\u0131ld\u0131\u011f\u0131 gibi olmas\u0131", "averagePoint1": "4.9 / 5", "numberOfReviews1": "496", "label2": "Sat\u0131c\u0131n\u0131n al\u0131c\u0131yla olan ileti\u015fimi", "averagePoint2": "4.7 / 5", "numberOfReviews2": "496", "label3": "\u00dcr\u00fcn\u00fcn zaman\u0131nda kargoya verilmesi", "averagePoint3": "4.8 / 5", "numberOfReviews3": "496", "label4": "\u00dcr\u00fcn\u00fcn kargo \u00fccreti", "averagePoint4": "5 / 5", "numberOfReviews4": "2", "label5": "\u00dcr\u00fcn\u00fcn kargo (ta\u015f\u0131ma, teslimat) hizmeti", "averagePoint5": "4.5 / 5", "numberOfReviews5": "496"}}}, {"products": {"product": [{"name": "Bosch Class 2000 W 22 Kw (19.000 Kcal) Hermetik Kombi", "price": "1.842,90                                                                                                        TL", "category": "Ana Sayfa\n                                \n\n\n\n\n\n                                        Elektronik                                     \n\n\n\n\n\n                                        Beyaz E\u015fya & K\u00fc\u00e7\u00fck Ev Aletleri                                     \n\n\n\n\n\n                                        Is\u0131tma, So\u011futma Sistemi                                     \n\n\n\n\n\n                                        Kombi                                     \n\n\n\n\n\n                                        Bosch Kombi                                    \n\n\n\n\n\n                                        Bosch Class 2000 W 22 KW", "shipment": "\u00dccretsiz - Ayn\u0131 G\u00fcn Kargo"}, {"name": "Airfel Digifix Duo KM1-24CE Hermetik Kombi (20000 kcal) 24 kw", "price": "1.614,05                                                                                                        TL", "category": "Ana Sayfa\n                                \n\n\n\n\n\n                                        Elektronik                                     \n\n\n\n\n\n                                        Beyaz E\u015fya & K\u00fc\u00e7\u00fck Ev Aletleri                                     \n\n\n\n\n\n                                        Is\u0131tma, So\u011futma Sistemi                                     \n\n\n\n\n\n                                        Kombi                                     \n\n\n\n\n\n                                        Airfel Kombi                                    \n\n\n\n\n\n                                        Airfel Digifix Duo KM1 24CE", "shipment": "\u00dccretsiz - Ayn\u0131 G\u00fcn Kargo"}, {"name": "Bosch Condens 2000 W Yo\u011fu\u015fmal\u0131 Kombi 24 kw 20.000 kcal", "price": "2.421,55                                                                                                        TL", "category": "Ana Sayfa\n                                \n\n\n\n\n\n                                        Elektronik                                     \n\n\n\n\n\n                                        Beyaz E\u015fya & K\u00fc\u00e7\u00fck Ev Aletleri                                     \n\n\n\n\n\n                                        Is\u0131tma, So\u011futma Sistemi                                     \n\n\n\n\n\n                                        Kombi                                     \n\n\n\n\n\n                                        Bosch Kombi                                    \n\n\n\n\n\n                                        Bosch Condense 2000 W 24", "shipment": "\u00dccretsiz - Ertesi G\u00fcn Kargo"}, {"name": "Viessmann Vitodens 050 -T 25 Kw (21.500 KCALH)", "price": "2.602,05                                                                                                        TL", "category": "Ana Sayfa\n                                \n\n\n\n\n\n                                        Elektronik                                     \n\n\n\n\n\n                                        Beyaz E\u015fya & K\u00fc\u00e7\u00fck Ev Aletleri                                     \n\n\n\n\n\n                                        Is\u0131tma, So\u011futma Sistemi                                     \n\n\n\n\n\n                                        Kombi                                     \n\n\n\n\n\n                                        Viessmann Kombi                                    \n\n\n\n\n\n                                        Viessmann Vitodens 050 t 25 Kw", "shipment": "\u00dccretsiz - Ertesi G\u00fcn Kargo"}, {"name": "ECA Proteus Premix Yo\u011fu\u015fmal\u0131 Kombi ERP 24 kW 20.000 kcal", "price": "3.099,00                                                                                                        TL", "category": "Ana Sayfa\n                                \n\n\n\n\n\n                                        Elektronik                                     \n\n\n\n\n\n                                        Beyaz E\u015fya & K\u00fc\u00e7\u00fck Ev Aletleri                                     \n\n\n\n\n\n                                        Is\u0131tma, So\u011futma Sistemi                                     \n\n\n\n\n\n                                        Kombi                                     \n\n\n\n\n\n                                        E.C.A. Kombi                                    \n\n\n\n\n\n                                        E.C.A. Proteus Premix 24 HM", "shipment": "\u00dccretsiz - Ertesi G\u00fcn Kargo"}, {"name": "Airfel Digifel Duo KM1-24CE Hermetik Kombi Yeni Model (20000 kcal) 24 kw", "price": "1.680,55                                                                                                        TL", "category": "Ana Sayfa\n                                \n\n\n\n\n\n                                        Elektronik                                     \n\n\n\n\n\n                                        Beyaz E\u015fya & K\u00fc\u00e7\u00fck Ev Aletleri                                     \n\n\n\n\n\n                                        Is\u0131tma, So\u011futma Sistemi                                     \n\n\n\n\n\n                                        Kombi                                     \n\n\n\n\n\n                                        Airfel Kombi                                    \n\n\n\n\n\n                                        Airfel Digifel Duo KB2 24 CE", "shipment": "\u00dccretsiz - Ertesi G\u00fcn Kargo"}, {"name": "Vaillant Ecofit Start 246 -1 Yo\u011fu\u015fmal\u0131 Kombi 24 KW (20.000kcal)", "price": "2.649,55                                                                                                        TL", "category": "Ana Sayfa\n                                \n\n\n\n\n\n                                        Elektronik                                     \n\n\n\n\n\n                                        Beyaz E\u015fya & K\u00fc\u00e7\u00fck Ev Aletleri                                     \n\n\n\n\n\n                                        Is\u0131tma, So\u011futma Sistemi                                     \n\n\n\n\n\n                                        Kombi                                     \n\n\n\n\n\n                                        Vaillant Kombi                                    \n\n\n\n\n\n                                        Vaillant ecoFIT Start VUW 246", "shipment": "\u00dccretsiz - Ertesi G\u00fcn Kargo"}, {"name": "Bosch Condens 2500 W Yo\u011fu\u015fmal\u0131 Kombi 24kw 20.000kcal", "price": "3.149,00                                                                                                        TL", "category": "Ana Sayfa\n                                \n\n\n\n\n\n                                        Elektronik                                     \n\n\n\n\n\n                                        Beyaz E\u015fya & K\u00fc\u00e7\u00fck Ev Aletleri                                     \n\n\n\n\n\n                                        Is\u0131tma, So\u011futma Sistemi                                     \n\n\n\n\n\n                                        Kombi                                     \n\n\n\n\n\n                                        Bosch Kombi                                    \n\n\n\n\n\n                                        Bosch Condense 2500 W 24", "shipment": "\u00dccretsiz - Ayn\u0131 G\u00fcn Kargo"}, {"name": "Demird\u00f6k\u00fcm Nitron Condense P 24 Yo\u011fu\u015fmal\u0131 Kombi (20.000 kcal)", "price": "2.611,55                                                                                                        TL", "category": "Ana Sayfa\n                                \n\n\n\n\n\n                                        Elektronik                                     \n\n\n\n\n\n                                        Beyaz E\u015fya & K\u00fc\u00e7\u00fck Ev Aletleri                                     \n\n\n\n\n\n                                        Is\u0131tma, So\u011futma Sistemi                                     \n\n\n\n\n\n                                        Kombi                                     \n\n\n\n\n\n                                        Demird\u00f6k\u00fcm Kombi                                    \n\n\n\n\n\n                                        Demird\u00f6k\u00fcm Nitron Condense P 24", "shipment": "\u00dccretsiz - Ayn\u0131 G\u00fcn Kargo"}, {"name": "Cosa Ak\u0131ll\u0131 Oda Termostat\u0131 Kombi Kiti", "price": "249,00                                                                                                        TL", "category": "Ana Sayfa\n                                \n\n\n\n\n\n                                        Elektronik                                     \n\n\n\n\n\n                                        Beyaz E\u015fya & K\u00fc\u00e7\u00fck Ev Aletleri                                     \n\n\n\n\n\n                                        Is\u0131tma, So\u011futma Sistemi                                     \n\n\n\n\n\n                                        Termostat                                     \n\n\n\n\n\n                                        General Termostat", "shipment": "\u00dccretsiz - Ayn\u0131 G\u00fcn Kargo"}, {"name": "Demird\u00f6k\u00fcm Nitromix P 24 Yo\u011fu\u015fmal\u0131 Kombi 24kw 20.000 kcal", "price": "3.229,00                                                                                                        TL", "category": "Ana Sayfa\n                                \n\n\n\n\n\n                                        Elektronik                                     \n\n\n\n\n\n                                        Beyaz E\u015fya & K\u00fc\u00e7\u00fck Ev Aletleri                                     \n\n\n\n\n\n                                        Is\u0131tma, So\u011futma Sistemi                                     \n\n\n\n\n\n                                        Kombi                                     \n\n\n\n\n\n                                        Demird\u00f6k\u00fcm Kombi                                    \n\n\n\n\n\n                                        Demird\u00f6k\u00fcm Nitromix P 24", "shipment": "\u00dccretsiz - Ertesi G\u00fcn Kargo"}, {"name": "Demird\u00f6k\u00fcm Nitron Condense P 28 Yo\u011fu\u015fmal\u0131 Kombi (24.000 kcal)", "price": "3.023,00                                                                                                        TL", "category": "Ana Sayfa\n                                \n\n\n\n\n\n                                        Elektronik                                     \n\n\n\n\n\n                                        Beyaz E\u015fya & K\u00fc\u00e7\u00fck Ev Aletleri                                     \n\n\n\n\n\n                                        Is\u0131tma, So\u011futma Sistemi                                     \n\n\n\n\n\n                                        Kombi                                     \n\n\n\n\n\n                                        Demird\u00f6k\u00fcm Kombi                                    \n\n\n\n\n\n                                        Demird\u00f6k\u00fcm Nitron Condense P 28", "shipment": "\u00dccretsiz - Ertesi G\u00fcn Kargo"}, {"name": "Viessmann Vitopend 100 Hermetik Kombi 24kw (20.000kcal)", "price": "2.355,05                                                                                                        TL", "category": "Ana Sayfa\n                                \n\n\n\n\n\n                                        Elektronik                                     \n\n\n\n\n\n                                        Beyaz E\u015fya & K\u00fc\u00e7\u00fck Ev Aletleri                                     \n\n\n\n\n\n                                        Is\u0131tma, So\u011futma Sistemi                                     \n\n\n\n\n\n                                        Kombi                                     \n\n\n\n\n\n                                        Viessmann Kombi                                    \n\n\n\n\n\n                                        Viessmann Vitopend 100 W 24.8", "shipment": "\u00dccretsiz - Ertesi G\u00fcn Kargo"}, {"name": "Demird\u00f6k\u00fcm RF 6001 Kablosuz Oda Termostat\u0131", "price": "152,50                                                                                                        TL", "category": "Ana Sayfa\n                                \n\n\n\n\n\n                                        Elektronik                                     \n\n\n\n\n\n                                        Beyaz E\u015fya & K\u00fc\u00e7\u00fck Ev Aletleri                                     \n\n\n\n\n\n                                        Is\u0131tma, So\u011futma Sistemi                                     \n\n\n\n\n\n                                        Termostat                                     \n\n\n\n\n\n                                        Demird\u00f6k\u00fcm Termostat", "shipment": "\u00dccretsiz - Ayn\u0131 G\u00fcn Kargo"}, {"name": "Gaz Alarm Cihazi (do\u011falgaz / Lpg) Gaz Alarm Cihaz", "price": "34,99                                                                                                        TL", "category": "Ana Sayfa\n                                \n\n\n\n\n\n                                        Elektronik                                     \n\n\n\n\n\n                                        Beyaz E\u015fya & K\u00fc\u00e7\u00fck Ev Aletleri                                     \n\n\n\n\n\n                                        Ev G\u00fcvenlik Sistemleri                                     \n\n\n\n\n\n                                        Duman, Gaz Dedekt\u00f6r\u00fc", "shipment": "\u00dccretsiz - Ertesi G\u00fcn Kargo"}, {"name": "Bosch TR 24 RF Kablosuz Oda Termostat\u0131", "price": "380,00                                                                                                        TL", "category": "Ana Sayfa\n                                \n\n\n\n\n\n                                        Elektronik                                     \n\n\n\n\n\n                                        Beyaz E\u015fya & K\u00fc\u00e7\u00fck Ev Aletleri                                     \n\n\n\n\n\n                                        Is\u0131tma, So\u011futma Sistemi                                     \n\n\n\n\n\n                                        Termostat                                     \n\n\n\n\n\n                                        Bosch Termostat", "shipment": "\u00dccretsiz - Ertesi G\u00fcn Kargo"}, {"name": "ECA ERT 176 RF Kablosuz Oda Termostat\u0131", "price": "160,00                                                                                                        TL", "category": "Ana Sayfa\n                                \n\n\n\n\n\n                                        Elektronik                                     \n\n\n\n\n\n                                        Beyaz E\u015fya & K\u00fc\u00e7\u00fck Ev Aletleri                                     \n\n\n\n\n\n                                        Is\u0131tma, So\u011futma Sistemi                                     \n\n\n\n\n\n                                        Termostat                                     \n\n\n\n\n\n                                        E.C.A. Termostat", "shipment": "\u00dccretsiz - Ertesi G\u00fcn Kargo"}, {"name": "Demird\u00f6k\u00fcm Exacontrol 7R Kablosuz Oda Termostat\u0131", "price": "308,75                                                                                                        TL", "category": "Ana Sayfa\n                                \n\n\n\n\n\n                                        Elektronik                                     \n\n\n\n\n\n                                        Beyaz E\u015fya & K\u00fc\u00e7\u00fck Ev Aletleri                                     \n\n\n\n\n\n                                        Is\u0131tma, So\u011futma Sistemi                                     \n\n\n\n\n\n                                        Termostat                                     \n\n\n\n\n\n                                        Demird\u00f6k\u00fcm Termostat", "shipment": "\u00dccretsiz - Ertesi G\u00fcn Kargo"}, {"name": "Demird\u00f6k\u00fcm Nepto Hk T 224 Hermetik Kombi 20.000 kcal", "price": "1.879,00                                                                                                        TL", "category": "Ana Sayfa\n                                \n\n\n\n\n\n                                        Elektronik                                     \n\n\n\n\n\n                                        Beyaz E\u015fya & K\u00fc\u00e7\u00fck Ev Aletleri                                     \n\n\n\n\n\n                                        Is\u0131tma, So\u011futma Sistemi                                     \n\n\n\n\n\n                                        Kombi                                     \n\n\n\n\n\n                                        Demird\u00f6k\u00fcm Kombi                                    \n\n\n\n\n\n                                        Demird\u00f6k\u00fcm Nepto HK T 224", "shipment": "\u00dccretsiz - Ayn\u0131 G\u00fcn Kargo"}, {"name": "VA\u0130LLANT VAI 6-035 NW 12.000 BTU \u0130NVERTER KL\u0130MA", "price": "2.564,05                                                                                                        TL", "category": "Ana Sayfa\n                                \n\n\n\n\n\n                                        Elektronik                                     \n\n\n\n\n\n                                        Beyaz E\u015fya & K\u00fc\u00e7\u00fck Ev Aletleri                                     \n\n\n\n\n\n                                        Is\u0131tma, So\u011futma Sistemi                                     \n\n\n\n\n\n                                        Klima ve Aksesuarlar\u0131                                     \n\n\n\n\n\n                                        Klima                                     \n\n\n\n\n\n                                        Vaillant Klima                                    \n\n\n\n\n\n                                        Vaillant VAI 6-035 WN", "shipment": "\u00dccretsiz - 2-3 g\u00fcn i\u00e7inde kargo"}, {"name": "VA\u0130LLANT VAI 6-065 NW 24.000 BTU \u0130NVERTER KL\u0130MA", "price": "4.840,00                                                                                                        TL", "category": "Ana Sayfa\n                                \n\n\n\n\n\n                                        Elektronik                                     \n\n\n\n\n\n                                        Beyaz E\u015fya & K\u00fc\u00e7\u00fck Ev Aletleri                                     \n\n\n\n\n\n                                        Is\u0131tma, So\u011futma Sistemi                                     \n\n\n\n\n\n                                        Klima ve Aksesuarlar\u0131                                     \n\n\n\n\n\n                                        Klima                                     \n\n\n\n\n\n                                        Vaillant Klima                                    \n\n\n\n\n\n                                        Vaillant VAI 6-035 WN", "shipment": "\u00dccretsiz - 2-3 g\u00fcn i\u00e7inde kargo"}, {"name": "VA\u0130LLANT VAI 6-050 NW 18.000 BTU \u0130NVERTER KL\u0130MA", "price": "3.749,00                                                                                                        TL", "category": "Ana Sayfa\n                                \n\n\n\n\n\n                                        Elektronik                                     \n\n\n\n\n\n                                        Beyaz E\u015fya & K\u00fc\u00e7\u00fck Ev Aletleri                                     \n\n\n\n\n\n                                        Is\u0131tma, So\u011futma Sistemi                                     \n\n\n\n\n\n                                        Klima ve Aksesuarlar\u0131                                     \n\n\n\n\n\n                                        Klima                                     \n\n\n\n\n\n                                        Vaillant Klima                                    \n\n\n\n\n\n                                        Vaillant VAI 6-035 WN", "shipment": "\u00dccretsiz - 2-3 g\u00fcn i\u00e7inde kargo"}, {"name": "VA\u0130LLANT VAI 6-025 NW 9.000 BTU \u0130NVERTER KL\u0130MA", "price": "2.374,05                                                                                                        TL", "category": "Ana Sayfa\n                                \n\n\n\n\n\n                                        Elektronik                                     \n\n\n\n\n\n                                        Beyaz E\u015fya & K\u00fc\u00e7\u00fck Ev Aletleri                                     \n\n\n\n\n\n                                        Is\u0131tma, So\u011futma Sistemi                                     \n\n\n\n\n\n                                        Klima ve Aksesuarlar\u0131                                     \n\n\n\n\n\n                                        Klima                                     \n\n\n\n\n\n                                        Vaillant Klima                                    \n\n\n\n\n\n                                        Vaillant VAI 6-025 WN", "shipment": "\u00dccretsiz - 2-3 g\u00fcn i\u00e7inde kargo"}, {"name": "Viessmann Vitodens 50-W Yo\u011fu\u015fmal\u0131 Kombi 24 kw (20.000kcal)", "price": "3.870,00                                                                                                        TL", "category": "Ana Sayfa\n                                \n\n\n\n\n\n                                        Elektronik                                     \n\n\n\n\n\n                                        Beyaz E\u015fya & K\u00fc\u00e7\u00fck Ev Aletleri                                     \n\n\n\n\n\n                                        Is\u0131tma, So\u011futma Sistemi                                     \n\n\n\n\n\n                                        Kombi                                     \n\n\n\n\n\n                                        Viessmann Kombi                                    \n\n\n\n\n\n                                        Viessmann Vitodens 050 W 24", "shipment": "\u00dccretsiz - Ertesi G\u00fcn Kargo"}, {"name": "Vaillant ecoTEC Pure VUW 286 / 7-2 Yo\u011fu\u015fmal\u0131 Kombi ( 20.000 kcal )", "price": "4.179,00                                                                                                        TL", "category": "Ana Sayfa\n                                \n\n\n\n\n\n                                        Elektronik                                     \n\n\n\n\n\n                                        Beyaz E\u015fya & K\u00fc\u00e7\u00fck Ev Aletleri                                     \n\n\n\n\n\n                                        Is\u0131tma, So\u011futma Sistemi                                     \n\n\n\n\n\n                                        Kombi                                     \n\n\n\n\n\n                                        Vaillant Kombi                                    \n\n\n\n\n\n                                        Vaillant ecoTEC Pure VUW 286 / 7-2", "shipment": "\u00dccretsiz - Ertesi G\u00fcn Kargo"}, {"name": "Demird\u00f6k\u00fcm Nitromix P 28 Yo\u011fu\u015fmal\u0131 Kombi 28kw 24.000kcal", "price": "3.539,00                                                                                                        TL", "category": "Ana Sayfa\n                                \n\n\n\n\n\n                                        Elektronik                                     \n\n\n\n\n\n                                        Beyaz E\u015fya & K\u00fc\u00e7\u00fck Ev Aletleri                                     \n\n\n\n\n\n                                        Is\u0131tma, So\u011futma Sistemi                                     \n\n\n\n\n\n                                        Kombi                                     \n\n\n\n\n\n                                        Demird\u00f6k\u00fcm Kombi                                    \n\n\n\n\n\n                                        Demird\u00f6k\u00fcm Nitromix P 28", "shipment": "\u00dccretsiz - Ertesi G\u00fcn Kargo"}, {"name": "Buderus RC100 ODA Termostat\u0131 (Kablolu Mod\u00fclasyonlu)", "price": "265,05                                                                                                        TL", "category": "Ana Sayfa\n                                \n\n\n\n\n\n                                        Elektronik                                     \n\n\n\n\n\n                                        Beyaz E\u015fya & K\u00fc\u00e7\u00fck Ev Aletleri                                     \n\n\n\n\n\n                                        Is\u0131tma, So\u011futma Sistemi                                     \n\n\n\n\n\n                                        Termostat                                     \n\n\n\n\n\n                                        Buderus Termostat", "shipment": "\u00dccretsiz - Ayn\u0131 G\u00fcn Kargo"}, {"name": "Eca Proteus Plus Blue Kombi 24 KW (20.000 kcal/h)", "price": "1.994,05                                                                                                        TL", "category": "Ana Sayfa\n                                \n\n\n\n\n\n                                        Elektronik                                     \n\n\n\n\n\n                                        Beyaz E\u015fya & K\u00fc\u00e7\u00fck Ev Aletleri                                     \n\n\n\n\n\n                                        Is\u0131tma, So\u011futma Sistemi                                     \n\n\n\n\n\n                                        Kombi                                     \n\n\n\n\n\n                                        E.C.A. Kombi                                    \n\n\n\n\n\n                                        E.C.A. Proteus Plus PRP Blue 24 HM", "shipment": "\u00dccretsiz - Ertesi G\u00fcn Kargo"}, {"name": "Demird\u00f6k\u00fcm Atron H 28 Hermetik Kombi 28 kw 24.000 kcal", "price": "2.279,05                                                                                                        TL", "category": "Ana Sayfa\n                                \n\n\n\n\n\n                                        Elektronik                                     \n\n\n\n\n\n                                        Beyaz E\u015fya & K\u00fc\u00e7\u00fck Ev Aletleri                                     \n\n\n\n\n\n                                        Is\u0131tma, So\u011futma Sistemi                                     \n\n\n\n\n\n                                        Kombi                                     \n\n\n\n\n\n                                        Demird\u00f6k\u00fcm Kombi                                    \n\n\n\n\n\n                                        Demird\u00f6k\u00fcm Atron H 28", "shipment": "\u00dccretsiz - Ertesi G\u00fcn Kargo"}, {"name": "Vaillant ecofit 286/1 Yo\u011fu\u015fmal\u0131 Kombi 28kw 24.000 kcal", "price": "3.119,00                                                                                                        TL", "category": "Ana Sayfa\n                                \n\n\n\n\n\n                                        Elektronik                                     \n\n\n\n\n\n                                        Beyaz E\u015fya & K\u00fc\u00e7\u00fck Ev Aletleri                                     \n\n\n\n\n\n                                        Is\u0131tma, So\u011futma Sistemi                                     \n\n\n\n\n\n                                        Kombi                                     \n\n\n\n\n\n                                        Vaillant Kombi                                    \n\n\n\n\n\n                                        Vaillant ecoFIT Start 286", "shipment": "\u00dccretsiz - Ertesi G\u00fcn Kargo"}, {"name": "Eca Confeo Plus DCO 28 HM 24.000 kcal Kombi", "price": "2.231,55                                                                                                        TL", "category": "Ana Sayfa\n                                \n\n\n\n\n\n                                        Elektronik                                     \n\n\n\n\n\n                                        Beyaz E\u015fya & K\u00fc\u00e7\u00fck Ev Aletleri                                     \n\n\n\n\n\n                                        Is\u0131tma, So\u011futma Sistemi                                     \n\n\n\n\n\n                                        Kombi                                     \n\n\n\n\n\n                                        E.C.A. Kombi                                    \n\n\n\n\n\n                                        E.C.A. Confeo Plus 24 HM", "shipment": "\u00dccretsiz - Ertesi G\u00fcn Kargo"}, {"name": "Eca Confeo Plus DCO 24 HM 20.000 kcal Kombi", "price": "2.134,65                                                                                                        TL", "category": "Ana Sayfa\n                                \n\n\n\n\n\n                                        Elektronik                                     \n\n\n\n\n\n                                        Beyaz E\u015fya & K\u00fc\u00e7\u00fck Ev Aletleri                                     \n\n\n\n\n\n                                        Is\u0131tma, So\u011futma Sistemi                                     \n\n\n\n\n\n                                        Kombi                                     \n\n\n\n\n\n                                        E.C.A. Kombi                                    \n\n\n\n\n\n                                        E.C.A. Confeo Plus 24 HM", "shipment": "\u00dccretsiz - Ertesi G\u00fcn Kargo"}, {"name": "Protherm Lynx 24 Hermetik Kombi 24kw 20.000 kcal", "price": "1.690,05                                                                                                        TL", "category": "Ana Sayfa\n                                \n\n\n\n\n\n                                        Elektronik                                     \n\n\n\n\n\n                                        Beyaz E\u015fya & K\u00fc\u00e7\u00fck Ev Aletleri                                     \n\n\n\n\n\n                                        Is\u0131tma, So\u011futma Sistemi                                     \n\n\n\n\n\n                                        Kombi                                     \n\n\n\n\n\n                                        Protherm Kombi                                    \n\n\n\n\n\n                                        Protherm Lynx 24", "shipment": "\u00dccretsiz - Ertesi G\u00fcn Kargo"}, {"name": "Demird\u00f6k\u00fcm Atron H 24 Hermetik Kombi 20.000kcal", "price": "2.089,05                                                                                                        TL", "category": "Ana Sayfa\n                                \n\n\n\n\n\n                                        Elektronik                                     \n\n\n\n\n\n                                        Beyaz E\u015fya & K\u00fc\u00e7\u00fck Ev Aletleri                                     \n\n\n\n\n\n                                        Is\u0131tma, So\u011futma Sistemi                                     \n\n\n\n\n\n                                        Kombi                                     \n\n\n\n\n\n                                        Demird\u00f6k\u00fcm Kombi                                    \n\n\n\n\n\n                                        Demird\u00f6k\u00fcm Atron H 24", "shipment": "\u00dccretsiz - Ertesi G\u00fcn Kargo"}, {"name": "Kombi Alt Ba\u011flant\u0131 Seti 8 li Dirsekli", "price": "39,50                                                                                                        TL", "category": "Ana Sayfa\n                                \n\n\n\n\n\n                                        Ev, Bah\u00e7e ve Ofis                                     \n\n\n\n\n\n                                        Yap\u0131 Market & Tamirat                                     \n\n\n\n\n\n                                        Yap\u0131 Malzemeleri, Nalburiye                                     \n\n\n\n\n\n                                        Di\u011fer Yap\u0131 Malzemeleri", "shipment": "\u00dccretsiz - Ertesi G\u00fcn Kargo"}, {"name": "Buderus RT 24 Rf Kablosuz Oda Termostat\u0131", "price": "449,00                                                                                                        TL", "category": "Ana Sayfa\n                                \n\n\n\n\n\n                                        Elektronik                                     \n\n\n\n\n\n                                        Beyaz E\u015fya & K\u00fc\u00e7\u00fck Ev Aletleri                                     \n\n\n\n\n\n                                        Is\u0131tma, So\u011futma Sistemi                                     \n\n\n\n\n\n                                        Termostat                                     \n\n\n\n\n\n                                        Buderus Termostat", "shipment": "\u00dccretsiz - Ertesi G\u00fcn Kargo"}, {"name": "Eca Plustech Pt 24 Hm Yo\u011fu\u015fmal\u0131 Kombi 20.000 Kcal/h", "price": "2.469,05                                                                                                        TL", "category": "Ana Sayfa\n                                \n\n\n\n\n\n                                        Elektronik                                     \n\n\n\n\n\n                                        Beyaz E\u015fya & K\u00fc\u00e7\u00fck Ev Aletleri                                     \n\n\n\n\n\n                                        Is\u0131tma, So\u011futma Sistemi                                     \n\n\n\n\n\n                                        Kombi                                     \n\n\n\n\n\n                                        E.C.A. Kombi", "shipment": "\u00dccretsiz - Ertesi G\u00fcn Kargo"}, {"name": "Buderus RT 36 RF Kablosuz Programlanabilir Oda Termostat\u0131", "price": "575,00                                                                                                        TL", "category": "Ana Sayfa\n                                \n\n\n\n\n\n                                        Elektronik                                     \n\n\n\n\n\n                                        Beyaz E\u015fya & K\u00fc\u00e7\u00fck Ev Aletleri                                     \n\n\n\n\n\n                                        Is\u0131tma, So\u011futma Sistemi                                     \n\n\n\n\n\n                                        Termostat                                     \n\n\n\n\n\n                                        Buderus Termostat", "shipment": "\u00dccretsiz - Ertesi G\u00fcn Kargo"}, {"name": "Bosch CR 10 Mod\u00fclasyonlu Dijital Oda Termostat\u0131", "price": "225,00                                                                                                        TL", "category": "Ana Sayfa\n                                \n\n\n\n\n\n                                        Elektronik                                     \n\n\n\n\n\n                                        Beyaz E\u015fya & K\u00fc\u00e7\u00fck Ev Aletleri                                     \n\n\n\n\n\n                                        Is\u0131tma, So\u011futma Sistemi                                     \n\n\n\n\n\n                                        Termostat                                     \n\n\n\n\n\n                                        Bosch Termostat", "shipment": "\u00dccretsiz - Ertesi G\u00fcn Kargo"}, {"name": "Vaillant eRelax Wifi telefon Ak\u0131ll\u0131 Oda Termostat\u0131", "price": "1.049,00                                                                                                        TL", "category": "Ana Sayfa\n                                \n\n\n\n\n\n                                        Elektronik                                     \n\n\n\n\n\n                                        Beyaz E\u015fya & K\u00fc\u00e7\u00fck Ev Aletleri                                     \n\n\n\n\n\n                                        Is\u0131tma, So\u011futma Sistemi                                     \n\n\n\n\n\n                                        Termostat                                     \n\n\n\n\n\n                                        Vaillant Termostat", "shipment": "\u00dccretsiz - Ertesi G\u00fcn Kargo"}, {"name": "Kalde K\u00f6\u015fe Radyat\u00f6r Vanas\u0131 1/2", "price": "15,00                                                                                                        TL", "category": "Ana Sayfa\n                                \n\n\n\n\n\n                                        Ev, Bah\u00e7e ve Ofis                                     \n\n\n\n\n\n                                        Yap\u0131 Market & Tamirat                                     \n\n\n\n\n\n                                        Yap\u0131 Malzemeleri, Nalburiye                                     \n\n\n\n\n\n                                        Di\u011fer Yap\u0131 Malzemeleri", "shipment": "\u00dccretsiz - Ertesi G\u00fcn Kargo"}, {"name": "BOSCH TR 36 RF Programlanabilir Kablosuz Oda Termostat\u0131", "price": "502,55                                                                                                        TL", "category": "Ana Sayfa\n                                \n\n\n\n\n\n                                        Elektronik                                     \n\n\n\n\n\n                                        Beyaz E\u015fya & K\u00fc\u00e7\u00fck Ev Aletleri                                     \n\n\n\n\n\n                                        Is\u0131tma, So\u011futma Sistemi                                     \n\n\n\n\n\n                                        Termostat                                     \n\n\n\n\n\n                                        Bosch Termostat", "shipment": "\u00dccretsiz - Ertesi G\u00fcn Kargo"}, {"name": "Kalde K\u00f6\u015fe Radyat\u00f6r Vanas\u0131 1/2 ( 10 ADET )", "price": "119,00                                                                                                        TL", "category": "Ana Sayfa\n                                \n\n\n\n\n\n                                        Ev, Bah\u00e7e ve Ofis                                     \n\n\n\n\n\n                                        Yap\u0131 Market & Tamirat                                     \n\n\n\n\n\n                                        Yap\u0131 Malzemeleri, Nalburiye                                     \n\n\n\n\n\n                                        Di\u011fer Yap\u0131 Malzemeleri", "shipment": "\u00dccretsiz - Ertesi G\u00fcn Kargo"}, {"name": "Kombi Gaz Flexi 40cm", "price": "17,50                                                                                                        TL", "category": "Ana Sayfa\n                                \n\n\n\n\n\n                                        Ev, Bah\u00e7e ve Ofis                                     \n\n\n\n\n\n                                        Yap\u0131 Market & Tamirat                                     \n\n\n\n\n\n                                        Tamir, Tadilat Gere\u00e7leri                                     \n\n\n\n\n\n                                        Di\u011fer Tamir Gere\u00e7leri", "shipment": "\u00dccretsiz - Ertesi G\u00fcn Kargo"}, {"name": "Kombi Alt Ba\u011flant\u0131 Seti 8'li D\u00fcz", "price": "38,00                                                                                                        TL", "category": "Ana Sayfa\n                                \n\n\n\n\n\n                                        Ev, Bah\u00e7e ve Ofis                                     \n\n\n\n\n\n                                        Yap\u0131 Market & Tamirat                                     \n\n\n\n\n\n                                        Yap\u0131 Malzemeleri, Nalburiye                                     \n\n\n\n\n\n                                        Di\u011fer Yap\u0131 Malzemeleri", "shipment": "\u00dccretsiz - Ertesi G\u00fcn Kargo"}, {"name": "LYK\u0130A KL\u0130MA PARF\u00dcM\u00dc", "price": "29,90                                                                                                        TL", "category": "Ana Sayfa\n                                \n\n\n\n\n\n                                        Elektronik                                     \n\n\n\n\n\n                                        Beyaz E\u015fya & K\u00fc\u00e7\u00fck Ev Aletleri                                     \n\n\n\n\n\n                                        Beyaz E\u015fya                                     \n\n\n\n\n\n                                        Yedek Par\u00e7a ve Aksesuar", "shipment": "\u00dccretsiz - Ertesi G\u00fcn Kargo"}, {"name": "Kombi Alt Ba\u011flant\u0131 Seti 8 li Dirsekli", "price": "38,00                                                                                                        TL", "category": "Ana Sayfa\n                                \n\n\n\n\n\n                                        Ev, Bah\u00e7e ve Ofis                                     \n\n\n\n\n\n                                        Yap\u0131 Market & Tamirat                                     \n\n\n\n\n\n                                        Yap\u0131 Malzemeleri, Nalburiye                                     \n\n\n\n\n\n                                        Di\u011fer Yap\u0131 Malzemeleri", "shipment": "\u00dccretsiz - Ertesi G\u00fcn Kargo"}, {"name": "Kombi Gaz Flexi 50 CM", "price": "20,00                                                                                                        TL", "category": "Ana Sayfa\n                                \n\n\n\n\n\n                                        Ev, Bah\u00e7e ve Ofis                                     \n\n\n\n\n\n                                        Yap\u0131 Market & Tamirat                                     \n\n\n\n\n\n                                        Tamir, Tadilat Gere\u00e7leri                                     \n\n\n\n\n\n                                        Di\u011fer Tamir Gere\u00e7leri", "shipment": "\u00dccretsiz - Ertesi G\u00fcn Kargo"}, {"name": "Bosch Yo\u011fu\u015fmal\u0131 Orjinal 45 Derece Kombi Baca Dirse\u011fi", "price": "125,00                                                                                                        TL", "category": "Ana Sayfa\n                                \n\n\n\n\n\n                                        Di\u011fer Her \u015eey                                     \n\n\n\n\n\n                                        Di\u011fer Her \u015eey", "shipment": "\u00dccretsiz - 2-3 g\u00fcn i\u00e7inde kargo"}, {"name": "Bosch Yo\u011fu\u015fmal\u0131 Orjinal 50 CM Kombi Baca Uzatmas\u0131", "price": "100,00                                                                                                        TL", "category": "Ana Sayfa\n                                \n\n\n\n\n\n                                        Di\u011fer Her \u015eey                                     \n\n\n\n\n\n                                        Di\u011fer Her \u015eey", "shipment": "\u00dccretsiz - 2-3 g\u00fcn i\u00e7inde kargo"}, {"name": "Bosch Hermetik orjinal 90 Derece Kombi Baca Dirse\u011fi", "price": "100,00                                                                                                        TL", "category": "Ana Sayfa\n                                \n\n\n\n\n\n                                        Di\u011fer Her \u015eey                                     \n\n\n\n\n\n                                        Di\u011fer Her \u015eey", "shipment": "\u00dccretsiz - 2-3 g\u00fcn i\u00e7inde kargo"}, {"name": "Buderus Hermetik Orjinal 45 Derece Kombi Baca Dirse\u011fi", "price": "100,00                                                                                                        TL", "category": "Ana Sayfa\n                                \n\n\n\n\n\n                                        Di\u011fer Her \u015eey                                     \n\n\n\n\n\n                                        Di\u011fer Her \u015eey", "shipment": "\u00dccretsiz - 2-3 g\u00fcn i\u00e7inde kargo"}, {"name": "Buderus Hermetik 75cm Kombi Baca Uzatmas\u0131", "price": "125,00                                                                                                        TL", "category": "Ana Sayfa\n                                \n\n\n\n\n\n                                        Di\u011fer Her \u015eey                                     \n\n\n\n\n\n                                        Di\u011fer Her \u015eey", "shipment": "\u00dccretsiz - 2-3 g\u00fcn i\u00e7inde kargo"}, {"name": "Buderus Yo\u011fu\u015fmal\u0131 Orjinal 90 Derece Kombi Baca Dirse\u011fi", "price": "125,00                                                                                                        TL", "category": "Ana Sayfa\n                                \n\n\n\n\n\n                                        Di\u011fer Her \u015eey                                     \n\n\n\n\n\n                                        Di\u011fer Her \u015eey", "shipment": "\u00dccretsiz - 2-3 g\u00fcn i\u00e7inde kargo"}, {"name": "Bosch Hermetik Orjinal 45 Derece Kombi Baca Dirse\u011fi", "price": "115,00                                                                                                        TL", "category": "Ana Sayfa\n                                \n\n\n\n\n\n                                        Di\u011fer Her \u015eey                                     \n\n\n\n\n\n                                        Di\u011fer Her \u015eey", "shipment": "\u00dccretsiz - 2-3 g\u00fcn i\u00e7inde kargo"}, {"name": "Bosch Yo\u011fu\u015fmal\u0131 Orjinal 100CM Kombi Baca Uzatmas\u0131", "price": "150,00                                                                                                        TL", "category": "Ana Sayfa\n                                \n\n\n\n\n\n                                        Di\u011fer Her \u015eey                                     \n\n\n\n\n\n                                        Di\u011fer Her \u015eey", "shipment": "\u00dccretsiz - 2-3 g\u00fcn i\u00e7inde kargo"}, {"name": "Demird\u00f6k\u00fcm Exacontrol 7 Kablolu Oda Termostat\u0131", "price": "185,00                                                                                                        TL", "category": "Ana Sayfa\n                                \n\n\n\n\n\n                                        Elektronik                                     \n\n\n\n\n\n                                        Beyaz E\u015fya & K\u00fc\u00e7\u00fck Ev Aletleri                                     \n\n\n\n\n\n                                        Is\u0131tma, So\u011futma Sistemi                                     \n\n\n\n\n\n                                        Termostat                                     \n\n\n\n\n\n                                        Demird\u00f6k\u00fcm Termostat", "shipment": "\u00dccretsiz - Ertesi G\u00fcn Kargo"}, {"name": "BUDERUS RC150 Programlanabilir Kablolu Oda Termostat\u0131", "price": "369,55                                                                                                        TL", "category": "Ana Sayfa\n                                \n\n\n\n\n\n                                        Elektronik                                     \n\n\n\n\n\n                                        Beyaz E\u015fya & K\u00fc\u00e7\u00fck Ev Aletleri                                     \n\n\n\n\n\n                                        Is\u0131tma, So\u011futma Sistemi                                     \n\n\n\n\n\n                                        Termostat                                     \n\n\n\n\n\n                                        Buderus Termostat", "shipment": "\u00dccretsiz - Ertesi G\u00fcn Kargo"}, {"name": "Buderus Hermetik 35 cm Kombi Baca Uzatmas\u0131 orjinal", "price": "90,00                                                                                                        TL", "category": "Ana Sayfa\n                                \n\n\n\n\n\n                                        Di\u011fer Her \u015eey                                     \n\n\n\n\n\n                                        Di\u011fer Her \u015eey", "shipment": "\u00dccretsiz - Ertesi G\u00fcn Kargo"}, {"name": "DEM\u0130RD\u00d6K\u00dcM RF 6001 KABLOSUZ ODA TERMOSTATI", "price": "145,00                                                                                                        TL", "category": "Ana Sayfa\n                                \n\n\n\n\n\n                                        Elektronik                                     \n\n\n\n\n\n                                        Beyaz E\u015fya & K\u00fc\u00e7\u00fck Ev Aletleri                                     \n\n\n\n\n\n                                        Is\u0131tma, So\u011futma Sistemi                                     \n\n\n\n\n\n                                        Termostat                                     \n\n\n\n\n\n                                        Demird\u00f6k\u00fcm Termostat", "shipment": "Al\u0131c\u0131 \u00d6der - Ayn\u0131 G\u00fcn Kargo                                 \nT\u00fcm T\u00fcrkiye: 6,00 TL"}, {"name": "Bosch Hermetik 75cm Kombi Baca Uzatmas\u0131", "price": "140,00                                                                                                        TL", "category": "Ana Sayfa\n                                \n\n\n\n\n\n                                        Di\u011fer Her \u015eey                                     \n\n\n\n\n\n                                        Di\u011fer Her \u015eey", "shipment": "\u00dccretsiz - 2-3 g\u00fcn i\u00e7inde kargo"}]}}, {"comments": {"comment": [{"reviewer": "gemicidisa ( 3 )", "dateTime": "21/07/2018", "productName": "Demird\u00f6k\u00fcm Atron H 24 Hermetik Kombi 20.000kcal", "mood": "Mutlu", "text": "\n"}, {"reviewer": "alibeypazar ( 2 )", "dateTime": "20/07/2018", "productName": "Demird\u00f6k\u00fcm Nitron Condense P 24 Yo\u011fu\u015fmal\u0131 Kombi (20.000 kcal)", "mood": "Mutlu", "text": "\n                                        \u00c7ok h\u0131zl\u0131 geldi Te\u015fekk\u00fcrler yurti\u00e7i kargo \n                                    "}, {"reviewer": "hakanosman14 ( 6 )", "dateTime": "18/07/2018", "productName": "Demird\u00f6k\u00fcm Nitron Condense P 24 Yo\u011fu\u015fmal\u0131 Kombi (20.000 kcal)", "mood": "Mutlu", "text": "\n"}, {"reviewer": "selimsenler ( 51 )", "dateTime": "18/07/2018", "productName": "Demird\u00f6k\u00fcm Nitron Condense P 24 Yo\u011fu\u015fmal\u0131 Kombi (20.000 kcal)", "mood": "Mutlu", "text": "\n"}, {"reviewer": "fotomarko ( 15 )", "dateTime": "18/07/2018", "productName": "Demird\u00f6k\u00fcm Nitron Condense P 24 Yo\u011fu\u015fmal\u0131 Kombi (20.000 kcal)", "mood": "Mutlu", "text": "\n                                        cok te\u015fek\u00fcrler h\u0131zl\u0131 kargo sorunsuz \u00fcr\u00fcn \n                                    "}, {"reviewer": "ilkersahin23 ( 18 )", "dateTime": "17/07/2018", "productName": "Demird\u00f6k\u00fcm Nitron Condense P 24 Yo\u011fu\u015fmal\u0131 Kombi (20.000 kcal)", "mood": "Mutlu", "text": "\n"}, {"reviewer": "akin_yusuf13 ( 13 )", "dateTime": "16/07/2018", "productName": "Demird\u00f6k\u00fcm Nitron Condense P 24 Yo\u011fu\u015fmal\u0131 Kombi (20.000 kcal)", "mood": "Mutlu", "text": "\n"}, {"reviewer": "kirazozkan ( 30 )", "dateTime": "15/07/2018", "productName": "Viessmann Vitopend 100 Hermetik Kombi 24kw (20.000kcal)", "mood": "Mutlu", "text": "\n                                        Sorunsuz bir al\u0131\u015fveri\u015f oldu. Sat\u0131\u015f sonras\u0131 hizmet \u00e7ok iyi. Te\u015fekk\u00fcrler \n                                    "}, {"reviewer": "eneszengin15 ( 43 )", "dateTime": "14/07/2018", "productName": "Airfel Digifix Duo KM1-24CE Hermetik Kombi (20000 kcal) 24 kw", "mood": "Mutlu", "text": "\n                                        \u00dcr\u00fcnden daha \u00f6nce de 3 adet ald\u0131m. Bu 4. Al\u0131\u015f\u0131m memnunum genel olarak. Kargo h\u0131zl\u0131 ve \u00fccretsiz. Piyasadan 150 tl a\u015fa\u011f\u0131. \u015eikayetim yok hi\u00e7 bi \u015fekilde. Sat\u0131c\u0131dan genel olarak memnun. Gayet ilgili. Ve ayn\u0131 sat\u0131c\u0131y\u0131 tercih ettim. Sizde \u015fa\u015fmay\u0131n derim :) \n                                    "}, {"reviewer": "acizanehaci8527 ( 2 )", "dateTime": "14/07/2018", "productName": "Demird\u00f6k\u00fcm Nitromix P 24 Yo\u011fu\u015fmal\u0131 Kombi 24kw 20.000 kcal", "mood": "Mutlu", "text": "\n"}, {"reviewer": "l***n ( 73 )", "dateTime": "12/07/2018", "productName": "Gaz Alarm Cihazi (do\u011falgaz / Lpg) Gaz Alarm Cihaz", "mood": "Mutlu", "text": "\n"}, {"reviewer": "muratkargi003 ( 1 )", "dateTime": "11/07/2018", "productName": "DEM\u0130RD\u00d6K\u00dcM RF 6001 KABLOSUZ ODA TERMOSTATI", "mood": "Mutlu", "text": "\n                                        t\u015fk ediyorum g\u00fcvenli al\u0131\u015fveri\u015f &#128077;\n                                    "}, {"reviewer": "salmanavspor ( 78 )", "dateTime": "11/07/2018", "productName": "Gaz Alarm Cihazi (do\u011falgaz / Lpg) Gaz Alarm Cihaz", "mood": "Mutlu", "text": "\n"}, {"reviewer": "s2c112 ( 12 )", "dateTime": "10/07/2018", "productName": "Bosch Class 2000 W 22 Kw (19.000 Kcal) Hermetik Kombi", "mood": "Mutlu", "text": "\n"}, {"reviewer": "kylmz53 ( 2 )", "dateTime": "05/07/2018", "productName": "Bosch Class 2000 W 22 Kw (19.000 Kcal) Hermetik Kombi", "mood": "Mutlu", "text": "\n                                        \u00dcr\u00fcn\u00fc teslim ald\u0131m\n                                    "}, {"reviewer": "efs35 ( 11 )", "dateTime": "05/07/2018", "productName": "Bosch Condens 2000 W Yo\u011fu\u015fmal\u0131 Kombi 24 kw 20.000 kcal", "mood": "Mutlu", "text": "\n                                        ayn\u0131 g\u00fcn i\u00e7inde kargo 24 saatte teslim \n                                    "}, {"reviewer": "gulilhan07 ( 5 )", "dateTime": "03/07/2018", "productName": "Demird\u00f6k\u00fcm Nitron Condense P 24 Yo\u011fu\u015fmal\u0131 Kombi (20.000 kcal)", "mood": "Mutlu", "text": "\n"}, {"reviewer": "r***7 ( 112 )", "dateTime": "02/07/2018", "productName": "Viessmann Vitodens 50-W Yo\u011fu\u015fmal\u0131 Kombi 24 kw (20.000kcal)", "mood": "Mutlu", "text": "\n                                        \u00fcr\u00fcn hen\u00fcz ba\u011flanmad\u0131, a\u00e7\u0131p denemedi\u011fim i\u00e7in \u00fcr\u00fcn hakk\u0131nda yorum yapamayaca\u011f\u0131m fakat sat\u0131c\u0131n\u0131n ilgisi i\u00e7in ve \u00f6n\u00fcm\u00fcz pazar g\u00fcn\u00fc olmas\u0131na ra\u011fmen 2 g\u00fcnde elime ula\u015fan h\u0131zl\u0131 kargolama i\u00e7in \u00e7ok te\u015fekk\u00fcr ederim. \n                                    "}]}}, {"comments": {"comment": [{"reviewer": "k***_ ( 55 )", "dateTime": "28/06/2018", "productName": "BOSCH TR 24 RF KABLOSUZ ODA TERMOSTATI", "mood": "Mutlu", "text": "\n                                        Ge\u00e7 onay i\u00e7in \u00f6z\u00fcr dilerim. G\u00fczel al\u0131\u015fveri\u015f oldu. T\u015fk.\n                                    "}, {"reviewer": "faruk1493 ( 26 )", "dateTime": "28/06/2018", "productName": "Demird\u00f6k\u00fcm Exacontrol 7R Kablosuz Oda Termostat\u0131", "mood": "Mutlu", "text": "\n"}, {"reviewer": "a***l ( 22 )", "dateTime": "28/06/2018", "productName": "Gaz Alarm Cihazi (do\u011falgaz / Lpg) Gaz Alarm Cihaz", "mood": "Mutlu", "text": "\n                                        Kargonuzu ald\u0131m.Te\u015fekk\u00fcrlerimi bildiriyorum.\n                                    "}, {"reviewer": "cemsertbas ( 57 )", "dateTime": "27/06/2018", "productName": "Viessmann Vitopend 100 Hermetik Kombi 24kw (20.000kcal)", "mood": "Mutlu", "text": "\n"}, {"reviewer": "erkutolgun ( 45 )", "dateTime": "27/06/2018", "productName": "Demird\u00f6k\u00fcm Nitromix P 24 Yo\u011fu\u015fmal\u0131 Kombi 24kw 20.000 kcal", "mood": "\u00dczg\u00fcn", "text": "\n                                        Demird\u00f6k\u00fcm kombi ald\u0131m \u00e7ok h\u0131zl\u0131 geldi g\u00fczel bacas\u0131 kombiyle ayr\u0131 kutuda geliyor bacanin ambalaj\u0131 k\u00f6t\u00fcyd\u00fc  insallah bir parcasi dusmemistir icinden montajda g\u00f6rece\u011fiz\n                                    "}, {"reviewer": "muhammetaliuser ( 22 )", "dateTime": "26/06/2018", "productName": "Airfel Digifix Duo KM1-24CE Hermetik Kombi (20000 kcal) 24 kw", "mood": "Mutlu", "text": "\n"}, {"reviewer": "fatmaafacan ( 7 )", "dateTime": "25/06/2018", "productName": "Airfel Digifix Duo KM1-24CE Hermetik Kombi (20000 kcal) 24 kw", "mood": "Mutlu", "text": "\n"}, {"reviewer": "selma1845 ( 8 )", "dateTime": "25/06/2018", "productName": "Viessmann Vitopend 100 Hermetik Kombi 24kw (20.000kcal)", "mood": "Mutlu", "text": "\n"}, {"reviewer": "hemid47 ( 5 )", "dateTime": "23/06/2018", "productName": "Demird\u00f6k\u00fcm Nitromix P 24 Yo\u011fu\u015fmal\u0131 Kombi 24kw 20.000 kcal", "mood": "Mutlu", "text": "\n"}, {"reviewer": "ozhanatas2000 ( 2 )", "dateTime": "22/06/2018", "productName": "Demird\u00f6k\u00fcm Exacontrol 7R Kablosuz Oda Termostat\u0131", "mood": "Mutlu", "text": "\n                                        2 gune geldi s\u0131k\u0131nt\u0131s\u0131z.\n                                    "}, {"reviewer": "yasarbiber2270 ( 5 )", "dateTime": "21/06/2018", "productName": "Viessmann Vitopend 100 Hermetik Kombi 24kw (20.000kcal)", "mood": "Mutlu", "text": "\n"}, {"reviewer": "mhmtclldnz ( 2 )", "dateTime": "21/06/2018", "productName": "Bosch Class 2000 W 22 Kw (19.000 Kcal) Hermetik Kombi", "mood": "Mutlu", "text": "\n                                        hesapl\u0131 \r\nh\u0131zl\u0131\r\nt\u015fkler.\n                                    "}, {"reviewer": "feridun3534 ( 3 )", "dateTime": "21/06/2018", "productName": "Demird\u00f6k\u00fcm Nitron Condense P 24 Yo\u011fu\u015fmal\u0131 Kombi (20.000 kcal)", "mood": "Mutlu", "text": "\n"}, {"reviewer": "mtaslicali ( 2 )", "dateTime": "21/06/2018", "productName": "Airfel Digifix Duo KM1-24CE Hermetik Kombi (20000 kcal) 24 kw", "mood": "Mutlu", "text": "\n                                        Olduk\u00e7a h\u0131zl\u0131 ula\u015ft\u0131, kargo s\u00fcrecinde de sorumlu davrand\u0131lar te\u015fekk\u00fcr\n                                    "}, {"reviewer": "zaferozturk76 ( 35 )", "dateTime": "20/06/2018", "productName": "Demird\u00f6k\u00fcm Nitron Plus 24 Hermetik Kombi 20.000 kcal", "mood": "Mutlu", "text": "\n                                        Do\u011fru \u00fcr\u00fcn, h\u0131zl\u0131 kargo,d\u00fcr\u00fcst sat\u0131c\u0131...\n                                    "}, {"reviewer": "thames ( 37 )", "dateTime": "20/06/2018", "productName": "Viessmann Vitopend 100 Hermetik Kombi 24kw (20.000kcal)", "mood": "Mutlu", "text": "\n                                        g\u00fcvenilir sat\u0131c\u0131 \u00fcr\u00fcn anlat\u0131ld\u0131\u011f\u0131 gibi...\n                                    "}, {"reviewer": "durdurhan ( 2 )", "dateTime": "20/06/2018", "productName": "Airfel Digifix Duo KM1-24CE Hermetik Kombi (20000 kcal) 24 kw", "mood": "Mutlu", "text": "\n"}, {"reviewer": "gokhankoyden88 ( 2 )", "dateTime": "20/06/2018", "productName": "Demird\u00f6k\u00fcm Nitromix P 24 Yo\u011fu\u015fmal\u0131 Kombi 24kw 20.000 kcal", "mood": "Mutlu", "text": "\n                                        Yap\u0131lan yorumlar\u0131 okuktan sonra almaya karar verdim \u00fcr\u00fcn\u00fcm geldi\u011finde do\u011fru karar vernidi\u011fimi anlad\u0131m te\u015fekk\u00fcrler\n                                    "}]}}, {"comments": {"comment": [{"reviewer": "ugrasakkus ( 4 )", "dateTime": "16/06/2018", "productName": "Airfel Digifix Duo KM1-24CE Hermetik Kombi (20000 kcal) 24 kw", "mood": "Mutlu", "text": "\n                                        Hep b\u00f6yle g\u00fczel d\u00fczg\u00fcn kal\u0131n  yani  al\u0131\u015f veri\u015f ahl\u00e2k\u0131n\u0131 hep koruyun hem YARADAN IN  emrini yerine getirmi\u015f olursunuz hem de insanlara g\u00fcven vermi\u015f olursunuz te\u015fekk\u00fcrler Gittigidiyor her \u015fey tam istedi\u011fim gibiydi ba\u015fka al\u0131\u015f veri\u015f te bulu\u015fmak \u00fczere h\u015f\u00e7kl\u0131n\n                                    "}, {"reviewer": "46hakanaltun46 ( 47 )", "dateTime": "14/06/2018", "productName": "Bosch Class 2000 W 22 Kw (19.000 Kcal) Hermetik Kombi", "mood": "Mutlu", "text": "\n"}, {"reviewer": "rainman5978 ( 1 )", "dateTime": "13/06/2018", "productName": "Airfel Digifix Duo KM1-24CE Hermetik Kombi (20000 kcal) 24 kw", "mood": "Mutlu", "text": "\n"}, {"reviewer": "nizam2674 ( 8 )", "dateTime": "13/06/2018", "productName": "Vaillant Ecofit Start 246 -1 Yo\u011fu\u015fmal\u0131 Kombi 24 KW (20.000kcal)", "mood": "Mutlu", "text": "\n                                        G\u00fczel bi \u00fcr\u00fcn kargo \u015firketi hari\u00e7.\n                                    "}, {"reviewer": "acar041 ( 28 )", "dateTime": "11/06/2018", "productName": "Demird\u00f6k\u00fcm Nitromix P 24 Yo\u011fu\u015fmal\u0131 Kombi 24kw 20.000 kcal", "mood": "Mutlu", "text": "\n"}]}}, {"comments": {"comment": [{"reviewer": "frhtclk3445 ( 1 )", "dateTime": "09/06/2018", "productName": "Kalde K\u00f6\u015fe Radyat\u00f6r Vanas\u0131 1/2 ( 8 ADET )", "mood": "Mutlu", "text": "\n"}, {"reviewer": "ukaraagac ( 111 )", "dateTime": "08/06/2018", "productName": "Gaz Alarm Cihazi (do\u011falgaz / Lpg) Gaz Alarm Cihaz", "mood": "Mutlu", "text": "\n"}, {"reviewer": "dndsytrk ( 3 )", "dateTime": "08/06/2018", "productName": "Airfel Digifix Duo KM1-24CE Hermetik Kombi (20000 kcal) 24 kw", "mood": "Mutlu", "text": "\n"}, {"reviewer": "imiimirza ( 8 )", "dateTime": "08/06/2018", "productName": "Airfel Digifix Duo KM1-24CE Hermetik Kombi (20000 kcal) 24 kw", "mood": "\u00dczg\u00fcn", "text": "\n                                        Te\u015fekk\u00fcr ederim\n\n                                    "}, {"reviewer": "maralhan ( 3 )", "dateTime": "07/06/2018", "productName": "Gaz Alarm Cihazi (do\u011falgaz / Lpg) Gaz Alarm Cihaz", "mood": "Mutlu", "text": "\n"}, {"reviewer": "uzuncaorman54 ( 13 )", "dateTime": "05/06/2018", "productName": "Kalde K\u00f6\u015fe Radyat\u00f6r Vanas\u0131 1/2 ( 8 ADET )", "mood": "Mutlu", "text": "\n"}, {"reviewer": "serdarnevri ( 93 )", "dateTime": "05/06/2018", "productName": "Bosch Condens 2000 W Yo\u011fu\u015fmal\u0131 Kombi 24 kw 20.000 kcal", "mood": "Mutlu", "text": "\n"}, {"reviewer": "mesutcelebi9188 ( 1 )", "dateTime": "04/06/2018", "productName": "Demird\u00f6k\u00fcm Nitron Condense P 24 Yo\u011fu\u015fmal\u0131 Kombi (20.000 kcal)", "mood": "Mutlu", "text": "\n"}, {"reviewer": "burhanurcann ( 190 )", "dateTime": "02/06/2018", "productName": "Kalde K\u00f6\u015fe Radyat\u00f6r Vanas\u0131 1/2 ( 8 ADET )", "mood": "Mutlu", "text": "\n"}, {"reviewer": "hsndizdar ( 46 )", "dateTime": "02/06/2018", "productName": "Viessmann Vitopend 100 Hermetik Kombi 24kw (20.000kcal)", "mood": "Mutlu", "text": "\n                                        Sipar\u0131\u015f\u0131 Gece 23:30 da verdim ettesi g\u00fcn \u00f6\u011flen 12 de \u00fcr\u00fcn teslime geldi \r\nyani S\u00dcPER:):):) ilgili bir sat\u0131c\u0131 tavsiye ederim\n                                    "}, {"reviewer": "burgaz3422 ( 8 )", "dateTime": "01/06/2018", "productName": "Bosch Class 2000 W 22 Kw (19.000 Kcal) Hermetik Kombi", "mood": "Mutlu", "text": "\n                                        H\u0131zl\u0131 teslimat i\u00e7in te\u015fekk\u00fcrler.\n                                    "}, {"reviewer": "nunal58outlookcom ( 11 )", "dateTime": "01/06/2018", "productName": "Airfel Digifix Duo KM1-24CE Hermetik Kombi (20000 kcal) 24 kw", "mood": "Mutlu", "text": "\n"}]}}]}